<?xml version="1.0" encoding="utf-8" ?>

<keywords>
	<keyword>Software Development</keyword>
	<keyword>Software Architecture</keyword>
	<keyword>Algorithm Development</keyword>
	<keyword>Project Management</keyword>
	<keyword>Residential Construction</keyword>
	<keyword>AutoCAD Development</keyword>
	<keyword>Simulation</keyword>
	<keyword>Machine Learning</keyword>
	<keyword>Artificial Intelligence</keyword>
	<keyword>Computational Physics</keyword>
	<keyword>Data Science</keyword>
	<!--<keyword>Numerical Integration</keyword>-->
	<keyword>Research</keyword>
	<!--<keyword>Drilling Dynamics</keyword>-->
	<!--<keyword></keyword>-->
</keywords>